cidr_man/__init__.py
cidr_man/cidr.py
cidr_man-1.5.4.dist-info/LICENSE
cidr_man-1.5.4.dist-info/METADATA
cidr_man-1.5.4.dist-info/WHEEL
cidr_man-1.5.4.dist-info/RECORD
