Metadata-Version: 2.3
Name: CIDR-Man
Version: 1.5.4
Summary: CIDR-Man is a high-performance ipaddress subnetting library designed to replace the built-in ipaddress library.
License: MIT
Keywords: cidr,routing,IPv6,IPv4,Networking,Network,ipaddress,ip,address
Author: Tim Armstrong
Author-email: tim@plaintextnerds.com
Maintainer: Tim Armstrong
Maintainer-email: tim@plaintextnerds.com
Requires-Python: >=3.8,<4.0
Classifier: Intended Audience :: Telecommunications Industry
Classifier: License :: OSI Approved :: MIT License
Classifier: Programming Language :: Python :: 3
Classifier: Programming Language :: Python :: 3.8
Classifier: Programming Language :: Python :: 3.9
Classifier: Programming Language :: Python :: 3.10
Classifier: Programming Language :: Python :: 3.11
Classifier: Programming Language :: Python :: 3.12
Classifier: Programming Language :: Python :: 3.13
Classifier: Programming Language :: Python :: Implementation
Classifier: Topic :: Internet
Classifier: Topic :: Software Development :: Libraries
Classifier: Topic :: Software Development :: Libraries :: Python Modules
Classifier: Topic :: System :: Networking
Classifier: Topic :: System :: Networking :: Firewalls
Project-URL: Homepage, https://gitlab.com/geoip.network/cidr_man
Project-URL: Repository, https://gitlab.com/geoip.network/cidr_man
